snowlance/__init__.py
snowlance/constants.py
snowlance/datatypes.py
snowlance/snowflake.py
snowlance/snowlance.py
snowlance/typecheck.py
snowlance/util.py
snowlance-0.1.0.dist-info/licenses/LICENSE
snowlance-0.1.0.dist-info/METADATA
snowlance-0.1.0.dist-info/WHEEL
snowlance-0.1.0.dist-info/top_level.txt
snowlance-0.1.0.dist-info/RECORD
