Metadata-Version: 2.4
Name: snowlance
Version: 0.1.0
Summary: A thread safe, monotonic, customizable, eazy to use SnowFlake ID generator
Home-page: https://github.com/guoxiaoyang11/snowlance
Author: guoxiaoyang11
Requires-Python: >=3.12
License-File: LICENSE
Provides-Extra: test
Requires-Dist: pytest>=8.4.0; extra == "test"
Requires-Dist: pytest-asyncio>=1.0.0; extra == "test"
Requires-Dist: pytest-cov>=6.1.1; extra == "test"
Dynamic: license-file
